[
    {
        "IssuedDate": [
            "01/22/90",
            {
                "tp": 0.0,
                "fp": 8.0,
                "fn": 0.0
            }
        ],
        "TotalAmount": [
            "6,402.88",
            {
                "tp": 8.0,
                "fp": 0.0,
                "fn": 0.0
            }
        ],
        "LineItem": [
            [
                [
                    {
                        "ItemUnitValue": [
                            "3,361.79",
                            {
                                "tp": 0.0,
                                "fp": 8.0,
                                "fn": 0.0
                            }
                        ],
                        "ItemTotal": [
                            "17,048.47",
                            {
                                "tp": 9.0,
                                "fp": 0.0,
                                "fn": 0.0
                            }
                        ],
                        "ItemDescription": [
                            "SALARIES WAGES",
                            {
                                "tp": 14.0,
                                "fp": 0.0,
                                "fn": 2.0
                            }
                        ],
                        "ItemUnitCount": [
                            "",
                            {
                                "tp": 0.0,
                                "fp": 0.0,
                                "fn": 0.0
                            }
                        ]
                    },
                    {
                        "tp": 23.0,
                        "fp": 8.0,
                        "fn": 2.0
                    }
                ],
                [
                    {
                        "ItemDescription": [
                            "BENEFITS",
                            {
                                "tp": 8.0,
                                "fp": 0.0,
                                "fn": 12.0
                            }
                        ],
                        "ItemUnitCount": [
                            "",
                            {
                                "tp": 0.0,
                                "fp": 0.0,
                                "fn": 0.0
                            }
                        ],
                        "ItemUnitValue": [
                            "",
                            {
                                "tp": 0.0,
                                "fp": 0.0,
                                "fn": 0.0
                            }
                        ],
                        "ItemTotal": [
                            "",
                            {
                                "tp": 0.0,
                                "fp": 0.0,
                                "fn": 12.0
                            }
                        ]
                    },
                    {
                        "tp": 8.0,
                        "fp": 0.0,
                        "fn": 24.0
                    }
                ],
                [
                    {
                        "ItemTotal": [
                            "19,267.96",
                            {
                                "tp": 9.0,
                                "fp": 0.0,
                                "fn": 0.0
                            }
                        ],
                        "ItemDescription": [
                            "EQUIPMENT",
                            {
                                "tp": 9.0,
                                "fp": 0.0,
                                "fn": 0.0
                            }
                        ],
                        "ItemUnitCount": [
                            "",
                            {
                                "tp": 0.0,
                                "fp": 0.0,
                                "fn": 0.0
                            }
                        ],
                        "ItemUnitValue": [
                            "",
                            {
                                "tp": 0.0,
                                "fp": 0.0,
                                "fn": 0.0
                            }
                        ]
                    },
                    {
                        "tp": 18.0,
                        "fp": 0.0,
                        "fn": 0.0
                    }
                ],
                [
                    {
                        "ItemUnitValue": [
                            "269.34",
                            {
                                "tp": 0.0,
                                "fp": 6.0,
                                "fn": 0.0
                            }
                        ],
                        "ItemTotal": [
                            "981.04",
                            {
                                "tp": 6.0,
                                "fp": 0.0,
                                "fn": 0.0
                            }
                        ],
                        "ItemDescription": [
                            "COMMUNICATIONS",
                            {
                                "tp": 14.0,
                                "fp": 0.0,
                                "fn": 0.0
                            }
                        ],
                        "ItemUnitCount": [
                            "",
                            {
                                "tp": 0.0,
                                "fp": 0.0,
                                "fn": 0.0
                            }
                        ]
                    },
                    {
                        "tp": 20.0,
                        "fp": 6.0,
                        "fn": 0.0
                    }
                ],
                [
                    {
                        "ItemUnitValue": [
                            "3.29",
                            {
                                "tp": 0.0,
                                "fp": 4.0,
                                "fn": 0.0
                            }
                        ],
                        "ItemTotal": [
                            "944.29",
                            {
                                "tp": 6.0,
                                "fp": 0.0,
                                "fn": 0.0
                            }
                        ],
                        "ItemDescription": [
                            "TRAVEL",
                            {
                                "tp": 6.0,
                                "fp": 0.0,
                                "fn": 0.0
                            }
                        ],
                        "ItemUnitCount": [
                            "",
                            {
                                "tp": 0.0,
                                "fp": 0.0,
                                "fn": 0.0
                            }
                        ]
                    },
                    {
                        "tp": 12.0,
                        "fp": 4.0,
                        "fn": 0.0
                    }
                ],
                [
                    {
                        "ItemUnitValue": [
                            "0.00",
                            {
                                "tp": 0.0,
                                "fp": 4.0,
                                "fn": 0.0
                            }
                        ],
                        "ItemTotal": [
                            "0",
                            {
                                "tp": 1.0,
                                "fp": 0.0,
                                "fn": 3.0
                            }
                        ],
                        "ItemDescription": [
                            "FILT",
                            {
                                "tp": 4.0,
                                "fp": 0.0,
                                "fn": 1.0
                            }
                        ],
                        "ItemUnitCount": [
                            "",
                            {
                                "tp": 0.0,
                                "fp": 0.0,
                                "fn": 0.0
                            }
                        ]
                    },
                    {
                        "tp": 5.0,
                        "fp": 4.0,
                        "fn": 4.0
                    }
                ],
                [
                    {
                        "ItemUnitValue": [
                            "32.00",
                            {
                                "tp": 0.0,
                                "fp": 5.0,
                                "fn": 0.0
                            }
                        ],
                        "ItemTotal": [
                            "160.00",
                            {
                                "tp": 6.0,
                                "fp": 0.0,
                                "fn": 0.0
                            }
                        ],
                        "ItemDescription": [
                            "LEASE RENTAL",
                            {
                                "tp": 12.0,
                                "fp": 0.0,
                                "fn": 2.0
                            }
                        ],
                        "ItemUnitCount": [
                            "",
                            {
                                "tp": 0.0,
                                "fp": 0.0,
                                "fn": 0.0
                            }
                        ]
                    },
                    {
                        "tp": 18.0,
                        "fp": 5.0,
                        "fn": 2.0
                    }
                ],
                [
                    {
                        "ItemTotal": [
                            "120.00",
                            {
                                "tp": 6.0,
                                "fp": 0.0,
                                "fn": 0.0
                            }
                        ],
                        "ItemDescription": [
                            "REPAIR MAINTENANCE",
                            {
                                "tp": 18.0,
                                "fp": 0.0,
                                "fn": 3.0
                            }
                        ],
                        "ItemUnitCount": [
                            "",
                            {
                                "tp": 0.0,
                                "fp": 0.0,
                                "fn": 0.0
                            }
                        ],
                        "ItemUnitValue": [
                            "",
                            {
                                "tp": 0.0,
                                "fp": 0.0,
                                "fn": 0.0
                            }
                        ]
                    },
                    {
                        "tp": 24.0,
                        "fp": 0.0,
                        "fn": 3.0
                    }
                ],
                [
                    {
                        "ItemUnitValue": [
                            "33.65",
                            {
                                "tp": 0.0,
                                "fp": 5.0,
                                "fn": 0.0
                            }
                        ],
                        "ItemTotal": [
                            "629.40",
                            {
                                "tp": 6.0,
                                "fp": 0.0,
                                "fn": 0.0
                            }
                        ],
                        "ItemDescription": [
                            "SERVICES PRINTING",
                            {
                                "tp": 8.0,
                                "fp": 9.0,
                                "fn": 0.0
                            }
                        ],
                        "ItemUnitCount": [
                            "",
                            {
                                "tp": 0.0,
                                "fp": 0.0,
                                "fn": 0.0
                            }
                        ]
                    },
                    {
                        "tp": 14.0,
                        "fp": 14.0,
                        "fn": 0.0
                    }
                ],
                [
                    {
                        "ItemUnitCount": [
                            "",
                            {
                                "tp": 0.0,
                                "fp": 0.0,
                                "fn": 0.0
                            }
                        ],
                        "ItemUnitValue": [
                            "",
                            {
                                "tp": 0.0,
                                "fp": 0.0,
                                "fn": 0.0
                            }
                        ],
                        "ItemTotal": [
                            "",
                            {
                                "tp": 0.0,
                                "fp": 0.0,
                                "fn": 5.0
                            }
                        ],
                        "ItemDescription": [
                            "",
                            {
                                "tp": 0.0,
                                "fp": 0.0,
                                "fn": 8.0
                            }
                        ]
                    },
                    {
                        "tp": 0.0,
                        "fp": 0.0,
                        "fn": 13.0
                    }
                ],
                [
                    {
                        "ItemTotal": [
                            "2,076.70",
                            {
                                "tp": 8.0,
                                "fp": 0.0,
                                "fn": 0.0
                            }
                        ],
                        "ItemDescription": [
                            "SUPPLIES",
                            {
                                "tp": 8.0,
                                "fp": 0.0,
                                "fn": 0.0
                            }
                        ],
                        "ItemUnitCount": [
                            "",
                            {
                                "tp": 0.0,
                                "fp": 0.0,
                                "fn": 0.0
                            }
                        ],
                        "ItemUnitValue": [
                            "",
                            {
                                "tp": 0.0,
                                "fp": 0.0,
                                "fn": 0.0
                            }
                        ]
                    },
                    {
                        "tp": 16.0,
                        "fp": 0.0,
                        "fn": 0.0
                    }
                ],
                [
                    {
                        "ItemTotal": [
                            "70,00",
                            {
                                "tp": 4.0,
                                "fp": 1.0,
                                "fn": 1.0
                            }
                        ],
                        "ItemDescription": [
                            "CONFERENCES",
                            {
                                "tp": 11.0,
                                "fp": 0.0,
                                "fn": 0.0
                            }
                        ],
                        "ItemUnitCount": [
                            "",
                            {
                                "tp": 0.0,
                                "fp": 0.0,
                                "fn": 0.0
                            }
                        ],
                        "ItemUnitValue": [
                            "",
                            {
                                "tp": 0.0,
                                "fp": 0.0,
                                "fn": 0.0
                            }
                        ]
                    },
                    {
                        "tp": 15.0,
                        "fp": 1.0,
                        "fn": 1.0
                    }
                ],
                [
                    {
                        "ItemTotal": [
                            "0.00",
                            {
                                "tp": 3.0,
                                "fp": 1.0,
                                "fn": 1.0
                            }
                        ],
                        "ItemDescription": [
                            "OTHER",
                            {
                                "tp": 5.0,
                                "fp": 0.0,
                                "fn": 0.0
                            }
                        ],
                        "ItemUnitCount": [
                            "",
                            {
                                "tp": 0.0,
                                "fp": 0.0,
                                "fn": 0.0
                            }
                        ],
                        "ItemUnitValue": [
                            "",
                            {
                                "tp": 0.0,
                                "fp": 0.0,
                                "fn": 0.0
                            }
                        ]
                    },
                    {
                        "tp": 8.0,
                        "fp": 1.0,
                        "fn": 1.0
                    }
                ],
                [
                    {
                        "ItemUnitValue": [
                            ",280.58",
                            {
                                "tp": 0.0,
                                "fp": 7.0,
                                "fn": 0.0
                            }
                        ],
                        "ItemTotal": [
                            "6,563.86",
                            {
                                "tp": 7.0,
                                "fp": 1.0,
                                "fn": 1.0
                            }
                        ],
                        "ItemDescription": [
                            "INDIRECT COSTS",
                            {
                                "tp": 14.0,
                                "fp": 0.0,
                                "fn": 0.0
                            }
                        ],
                        "ItemUnitCount": [
                            "",
                            {
                                "tp": 0.0,
                                "fp": 0.0,
                                "fn": 0.0
                            }
                        ]
                    },
                    {
                        "tp": 21.0,
                        "fp": 8.0,
                        "fn": 1.0
                    }
                ]
            ],
            {
                "tp": 202.0,
                "fp": 51.0,
                "fn": 51.0
            }
        ],
        "InvoiceNumber": [
            "",
            {
                "tp": 0.0,
                "fp": 0.0,
                "fn": 0.0
            }
        ]
    },
    {
        "tp": 210.0,
        "fp": 59.0,
        "fn": 51.0
    }
]
