[
    {
        "TotalAmount": [
            "2929",
            {
                "tp": 2.0,
                "fp": 2.0,
                "fn": 6.0
            }
        ],
        "LineItem": [
            [
                [
                    {
                        "ItemTotal": [
                            "3,326.49",
                            {
                                "tp": 2.0,
                                "fp": 6.0,
                                "fn": 7.0
                            }
                        ],
                        "ItemDescription": [
                            "Labor",
                            {
                                "tp": 5.0,
                                "fp": 0.0,
                                "fn": 0.0
                            }
                        ],
                        "ItemUnitCount": [
                            "",
                            {
                                "tp": 0.0,
                                "fp": 0.0,
                                "fn": 0.0
                            }
                        ],
                        "ItemUnitValue": [
                            "",
                            {
                                "tp": 0.0,
                                "fp": 0.0,
                                "fn": 0.0
                            }
                        ]
                    },
                    {
                        "tp": 7.0,
                        "fp": 6.0,
                        "fn": 7.0
                    }
                ],
                [
                    {
                        "ItemTotal": [
                            "$143.34",
                            {
                                "tp": 7.0,
                                "fp": 0.0,
                                "fn": 0.0
                            }
                        ],
                        "ItemDescription": [
                            "Duplicating Other",
                            {
                                "tp": 11.0,
                                "fp": 6.0,
                                "fn": 0.0
                            }
                        ],
                        "ItemUnitCount": [
                            "",
                            {
                                "tp": 0.0,
                                "fp": 0.0,
                                "fn": 0.0
                            }
                        ],
                        "ItemUnitValue": [
                            "",
                            {
                                "tp": 0.0,
                                "fp": 0.0,
                                "fn": 0.0
                            }
                        ]
                    },
                    {
                        "tp": 18.0,
                        "fp": 6.0,
                        "fn": 0.0
                    }
                ],
                [
                    {
                        "ItemUnitCount": [
                            "",
                            {
                                "tp": 0.0,
                                "fp": 0.0,
                                "fn": 0.0
                            }
                        ],
                        "ItemUnitValue": [
                            "",
                            {
                                "tp": 0.0,
                                "fp": 0.0,
                                "fn": 0.0
                            }
                        ],
                        "ItemTotal": [
                            "",
                            {
                                "tp": 0.0,
                                "fp": 0.0,
                                "fn": 7.0
                            }
                        ],
                        "ItemDescription": [
                            "",
                            {
                                "tp": 0.0,
                                "fp": 0.0,
                                "fn": 5.0
                            }
                        ]
                    },
                    {
                        "tp": 0.0,
                        "fp": 0.0,
                        "fn": 12.0
                    }
                ]
            ],
            {
                "tp": 25.0,
                "fp": 12.0,
                "fn": 19.0
            }
        ],
        "InvoiceNumber": [
            "3712016",
            {
                "tp": 7.0,
                "fp": 0.0,
                "fn": 0.0
            }
        ],
        "IssuedDate": [
            "",
            {
                "tp": 0.0,
                "fp": 0.0,
                "fn": 8.0
            }
        ]
    },
    {
        "tp": 34.0,
        "fp": 14.0,
        "fn": 33.0
    }
]
