[
    {
        "TotalAmount": [
            "84.7",
            {
                "tp": 4.0,
                "fp": 0.0,
                "fn": 4.0
            }
        ],
        "LineItem": [
            [
                [
                    {
                        "ItemDescription": [
                            "NEWSPAPER",
                            {
                                "tp": 2.0,
                                "fp": 7.0,
                                "fn": 6.0
                            }
                        ],
                        "ItemUnitCount": [
                            "",
                            {
                                "tp": 0.0,
                                "fp": 0.0,
                                "fn": 5.0
                            }
                        ],
                        "ItemUnitValue": [
                            "",
                            {
                                "tp": 0.0,
                                "fp": 0.0,
                                "fn": 5.0
                            }
                        ],
                        "ItemTotal": [
                            "",
                            {
                                "tp": 0.0,
                                "fp": 0.0,
                                "fn": 6.0
                            }
                        ]
                    },
                    {
                        "tp": 2.0,
                        "fp": 7.0,
                        "fn": 22.0
                    }
                ],
                [
                    {
                        "ItemUnitCount": [
                            "",
                            {
                                "tp": 0.0,
                                "fp": 0.0,
                                "fn": 0.0
                            }
                        ],
                        "ItemUnitValue": [
                            "",
                            {
                                "tp": 0.0,
                                "fp": 0.0,
                                "fn": 0.0
                            }
                        ],
                        "ItemTotal": [
                            "",
                            {
                                "tp": 0.0,
                                "fp": 0.0,
                                "fn": 6.0
                            }
                        ],
                        "ItemDescription": [
                            "",
                            {
                                "tp": 0.0,
                                "fp": 0.0,
                                "fn": 7.0
                            }
                        ]
                    },
                    {
                        "tp": 0.0,
                        "fp": 0.0,
                        "fn": 13.0
                    }
                ]
            ],
            {
                "tp": 2.0,
                "fp": 7.0,
                "fn": 35.0
            }
        ],
        "InvoiceNumber": [
            "02345",
            {
                "tp": 0.0,
                "fp": 5.0,
                "fn": 0.0
            }
        ],
        "IssuedDate": [
            "",
            {
                "tp": 0.0,
                "fp": 0.0,
                "fn": 0.0
            }
        ]
    },
    {
        "tp": 6.0,
        "fp": 12.0,
        "fn": 39.0
    }
]
