[
    {
        "IssuedDate": [
            "21,1994",
            {
                "tp": 5.0,
                "fp": 2.0,
                "fn": 10.0
            }
        ],
        "TotalAmount": [
            "419,136.88",
            {
                "tp": 9.0,
                "fp": 1.0,
                "fn": 1.0
            }
        ],
        "LineItem": [
            [
                [
                    {
                        "ItemUnitValue": [
                            "62,386.00",
                            {
                                "tp": 0.0,
                                "fp": 9.0,
                                "fn": 0.0
                            }
                        ],
                        "ItemTotal": [
                            "73,397.83",
                            {
                                "tp": 9.0,
                                "fp": 0.0,
                                "fn": 0.0
                            }
                        ],
                        "ItemDescription": [
                            "INSERTING",
                            {
                                "tp": 9.0,
                                "fp": 0.0,
                                "fn": 0.0
                            }
                        ],
                        "ItemUnitCount": [
                            "",
                            {
                                "tp": 0.0,
                                "fp": 0.0,
                                "fn": 0.0
                            }
                        ]
                    },
                    {
                        "tp": 18.0,
                        "fp": 9.0,
                        "fn": 0.0
                    }
                ],
                [
                    {
                        "ItemTotal": [
                            "5,719.55",
                            {
                                "tp": 7.0,
                                "fp": 1.0,
                                "fn": 1.0
                            }
                        ],
                        "ItemDescription": [
                            "MECHANICALS",
                            {
                                "tp": 11.0,
                                "fp": 0.0,
                                "fn": 0.0
                            }
                        ],
                        "ItemUnitCount": [
                            "",
                            {
                                "tp": 0.0,
                                "fp": 0.0,
                                "fn": 0.0
                            }
                        ],
                        "ItemUnitValue": [
                            "",
                            {
                                "tp": 0.0,
                                "fp": 0.0,
                                "fn": 0.0
                            }
                        ]
                    },
                    {
                        "tp": 18.0,
                        "fp": 1.0,
                        "fn": 1.0
                    }
                ],
                [
                    {
                        "ItemUnitValue": [
                            "118.65",
                            {
                                "tp": 0.0,
                                "fp": 6.0,
                                "fn": 0.0
                            }
                        ],
                        "ItemTotal": [
                            "139.59",
                            {
                                "tp": 6.0,
                                "fp": 0.0,
                                "fn": 0.0
                            }
                        ],
                        "ItemDescription": [
                            "COLOR XEROX",
                            {
                                "tp": 11.0,
                                "fp": 0.0,
                                "fn": 0.0
                            }
                        ],
                        "ItemUnitCount": [
                            "",
                            {
                                "tp": 0.0,
                                "fp": 0.0,
                                "fn": 0.0
                            }
                        ]
                    },
                    {
                        "tp": 17.0,
                        "fp": 6.0,
                        "fn": 0.0
                    }
                ],
                [
                    {
                        "ItemUnitValue": [
                            "11.484.CK)",
                            {
                                "tp": 0.0,
                                "fp": 10.0,
                                "fn": 0.0
                            }
                        ],
                        "ItemTotal": [
                            "13,510.93",
                            {
                                "tp": 9.0,
                                "fp": 0.0,
                                "fn": 0.0
                            }
                        ],
                        "ItemDescription": [
                            "TYPEStl FING",
                            {
                                "tp": 8.0,
                                "fp": 4.0,
                                "fn": 3.0
                            }
                        ],
                        "ItemUnitCount": [
                            "",
                            {
                                "tp": 0.0,
                                "fp": 0.0,
                                "fn": 0.0
                            }
                        ]
                    },
                    {
                        "tp": 17.0,
                        "fp": 14.0,
                        "fn": 3.0
                    }
                ],
                [
                    {
                        "ItemTotal": [
                            "27,603.04",
                            {
                                "tp": 9.0,
                                "fp": 0.0,
                                "fn": 0.0
                            }
                        ],
                        "ItemDescription": [
                            "ENGRAVING",
                            {
                                "tp": 9.0,
                                "fp": 0.0,
                                "fn": 0.0
                            }
                        ],
                        "ItemUnitCount": [
                            "",
                            {
                                "tp": 0.0,
                                "fp": 0.0,
                                "fn": 0.0
                            }
                        ],
                        "ItemUnitValue": [
                            "",
                            {
                                "tp": 0.0,
                                "fp": 0.0,
                                "fn": 0.0
                            }
                        ]
                    },
                    {
                        "tp": 18.0,
                        "fp": 0.0,
                        "fn": 0.0
                    }
                ],
                [
                    {
                        "ItemUnitValue": [
                            "54.014.08",
                            {
                                "tp": 0.0,
                                "fp": 9.0,
                                "fn": 0.0
                            }
                        ],
                        "ItemTotal": [
                            "63,547.57",
                            {
                                "tp": 8.0,
                                "fp": 1.0,
                                "fn": 1.0
                            }
                        ],
                        "ItemDescription": [
                            "P ERSONALl zatio n/keycodi n g",
                            {
                                "tp": 10.0,
                                "fp": 20.0,
                                "fn": 15.0
                            }
                        ],
                        "ItemUnitCount": [
                            "",
                            {
                                "tp": 0.0,
                                "fp": 0.0,
                                "fn": 0.0
                            }
                        ]
                    },
                    {
                        "tp": 18.0,
                        "fp": 30.0,
                        "fn": 16.0
                    }
                ],
                [
                    {
                        "ItemTotal": [
                            "121,585.99",
                            {
                                "tp": 10.0,
                                "fp": 0.0,
                                "fn": 0.0
                            }
                        ],
                        "ItemDescription": [
                            "PRINTING",
                            {
                                "tp": 8.0,
                                "fp": 0.0,
                                "fn": 0.0
                            }
                        ],
                        "ItemUnitCount": [
                            "",
                            {
                                "tp": 0.0,
                                "fp": 0.0,
                                "fn": 0.0
                            }
                        ],
                        "ItemUnitValue": [
                            "",
                            {
                                "tp": 0.0,
                                "fp": 0.0,
                                "fn": 0.0
                            }
                        ]
                    },
                    {
                        "tp": 18.0,
                        "fp": 0.0,
                        "fn": 0.0
                    }
                ],
                [
                    {
                        "ItemTotal": [
                            "110,273.64",
                            {
                                "tp": 10.0,
                                "fp": 0.0,
                                "fn": 0.0
                            }
                        ],
                        "ItemDescription": [
                            "POSTAGE",
                            {
                                "tp": 7.0,
                                "fp": 0.0,
                                "fn": 0.0
                            }
                        ],
                        "ItemUnitCount": [
                            "",
                            {
                                "tp": 0.0,
                                "fp": 0.0,
                                "fn": 0.0
                            }
                        ],
                        "ItemUnitValue": [
                            "",
                            {
                                "tp": 0.0,
                                "fp": 0.0,
                                "fn": 0.0
                            }
                        ]
                    },
                    {
                        "tp": 17.0,
                        "fp": 0.0,
                        "fn": 0.0
                    }
                ],
                [
                    {
                        "ItemTotal": [
                            "588.97",
                            {
                                "tp": 6.0,
                                "fp": 0.0,
                                "fn": 0.0
                            }
                        ],
                        "ItemDescription": [
                            "SHIPPING",
                            {
                                "tp": 8.0,
                                "fp": 0.0,
                                "fn": 0.0
                            }
                        ],
                        "ItemUnitCount": [
                            "",
                            {
                                "tp": 0.0,
                                "fp": 0.0,
                                "fn": 0.0
                            }
                        ],
                        "ItemUnitValue": [
                            "",
                            {
                                "tp": 0.0,
                                "fp": 0.0,
                                "fn": 0.0
                            }
                        ]
                    },
                    {
                        "tp": 14.0,
                        "fp": 0.0,
                        "fn": 0.0
                    }
                ]
            ],
            {
                "tp": 155.0,
                "fp": 60.0,
                "fn": 20.0
            }
        ],
        "InvoiceNumber": [
            "D-10-0501",
            {
                "tp": 9.0,
                "fp": 0.0,
                "fn": 0.0
            }
        ]
    },
    {
        "tp": 178.0,
        "fp": 63.0,
        "fn": 31.0
    }
]
