[
    {
        "IssuedDate": [
            "03/16/931",
            {
                "tp": 8.0,
                "fp": 1.0,
                "fn": 0.0
            }
        ],
        "LineItem": [
            [
                [
                    {
                        "ItemUnitCount": [
                            "",
                            {
                                "tp": 0.0,
                                "fp": 0.0,
                                "fn": 3.0
                            }
                        ],
                        "ItemUnitValue": [
                            "",
                            {
                                "tp": 0.0,
                                "fp": 0.0,
                                "fn": 4.0
                            }
                        ],
                        "ItemTotal": [
                            "",
                            {
                                "tp": 0.0,
                                "fp": 0.0,
                                "fn": 7.0
                            }
                        ],
                        "ItemDescription": [
                            "",
                            {
                                "tp": 0.0,
                                "fp": 0.0,
                                "fn": 33.0
                            }
                        ]
                    },
                    {
                        "tp": 0.0,
                        "fp": 0.0,
                        "fn": 47.0
                    }
                ],
                [
                    {
                        "ItemTotal": [
                            "$432.00",
                            {
                                "tp": 4.0,
                                "fp": 3.0,
                                "fn": 1.0
                            }
                        ],
                        "ItemDescription": [
                            "VM.I/E",
                            {
                                "tp": 6.0,
                                "fp": 0.0,
                                "fn": 22.0
                            }
                        ],
                        "ItemUnitCount": [
                            "",
                            {
                                "tp": 0.0,
                                "fp": 0.0,
                                "fn": 1.0
                            }
                        ],
                        "ItemUnitValue": [
                            "",
                            {
                                "tp": 0.0,
                                "fp": 0.0,
                                "fn": 4.0
                            }
                        ]
                    },
                    {
                        "tp": 10.0,
                        "fp": 3.0,
                        "fn": 28.0
                    }
                ],
                [
                    {
                        "ItemTotal": [
                            "$150.00,",
                            {
                                "tp": 7.0,
                                "fp": 1.0,
                                "fn": 0.0
                            }
                        ],
                        "ItemDescription": [
                            "NUMBER OFPACKAGE/CARTON",
                            {
                                "tp": 12.0,
                                "fp": 11.0,
                                "fn": 14.0
                            }
                        ],
                        "ItemUnitCount": [
                            "",
                            {
                                "tp": 0.0,
                                "fp": 0.0,
                                "fn": 1.0
                            }
                        ],
                        "ItemUnitValue": [
                            "",
                            {
                                "tp": 0.0,
                                "fp": 0.0,
                                "fn": 5.0
                            }
                        ]
                    },
                    {
                        "tp": 19.0,
                        "fp": 12.0,
                        "fn": 20.0
                    }
                ],
                [
                    {
                        "ItemUnitCount": [
                            "",
                            {
                                "tp": 0.0,
                                "fp": 0.0,
                                "fn": 1.0
                            }
                        ],
                        "ItemUnitValue": [
                            "",
                            {
                                "tp": 0.0,
                                "fp": 0.0,
                                "fn": 5.0
                            }
                        ],
                        "ItemTotal": [
                            "",
                            {
                                "tp": 0.0,
                                "fp": 0.0,
                                "fn": 5.0
                            }
                        ],
                        "ItemDescription": [
                            "",
                            {
                                "tp": 0.0,
                                "fp": 0.0,
                                "fn": 26.0
                            }
                        ]
                    },
                    {
                        "tp": 0.0,
                        "fp": 0.0,
                        "fn": 37.0
                    }
                ],
                [
                    {
                        "ItemUnitCount": [
                            "1",
                            {
                                "tp": 0.0,
                                "fp": 1.0,
                                "fn": 1.0
                            }
                        ],
                        "ItemTotal": [
                            "$75.00",
                            {
                                "tp": 6.0,
                                "fp": 0.0,
                                "fn": 0.0
                            }
                        ],
                        "ItemDescription": [
                            "FLOOR DISPLAYS",
                            {
                                "tp": 14.0,
                                "fp": 0.0,
                                "fn": 49.0
                            }
                        ],
                        "ItemUnitValue": [
                            "",
                            {
                                "tp": 0.0,
                                "fp": 0.0,
                                "fn": 5.0
                            }
                        ]
                    },
                    {
                        "tp": 20.0,
                        "fp": 1.0,
                        "fn": 55.0
                    }
                ]
            ],
            {
                "tp": 49.0,
                "fp": 16.0,
                "fn": 187.0
            }
        ],
        "TotalAmount": [
            "",
            {
                "tp": 0.0,
                "fp": 0.0,
                "fn": 6.0
            }
        ],
        "InvoiceNumber": [
            "",
            {
                "tp": 0.0,
                "fp": 0.0,
                "fn": 0.0
            }
        ]
    },
    {
        "tp": 57.0,
        "fp": 17.0,
        "fn": 193.0
    }
]
